{"nodes": [{"id": "inflight", "label": "inflight.js", "file_type": "code", "source_file": "apps\\electron\\node_modules\\promise-inflight\\inflight.js", "source_location": "L1"}, {"id": "inflight_inflight", "label": "inflight()", "file_type": "code", "source_file": "apps\\electron\\node_modules\\promise-inflight\\inflight.js", "source_location": "L13"}], "edges": [{"source": "inflight", "target": "inflight_inflight", "relation": "contains", "confidence": "EXTRACTED", "source_file": "apps\\electron\\node_modules\\promise-inflight\\inflight.js", "source_location": "L13", "weight": 1.0}]}