{"nodes": [{"id": "imageutils", "label": "imageUtils.js", "file_type": "code", "source_file": "apps\\frontend\\node_modules\\playwright-core\\lib\\utils\\isomorphic\\imageUtils.js", "source_location": "L1"}, {"id": "imageutils_padimagetosize", "label": "padImageToSize()", "file_type": "code", "source_file": "apps\\frontend\\node_modules\\playwright-core\\lib\\utils\\isomorphic\\imageUtils.js", "source_location": "L25"}, {"id": "imageutils_scaleimagetosize", "label": "scaleImageToSize()", "file_type": "code", "source_file": "apps\\frontend\\node_modules\\playwright-core\\lib\\utils\\isomorphic\\imageUtils.js", "source_location": "L48"}], "edges": [{"source": "imageutils", "target": "imageutils_padimagetosize", "relation": "contains", "confidence": "EXTRACTED", "source_file": "apps\\frontend\\node_modules\\playwright-core\\lib\\utils\\isomorphic\\imageUtils.js", "source_location": "L25", "weight": 1.0}, {"source": "imageutils", "target": "imageutils_scaleimagetosize", "relation": "contains", "confidence": "EXTRACTED", "source_file": "apps\\frontend\\node_modules\\playwright-core\\lib\\utils\\isomorphic\\imageUtils.js", "source_location": "L48", "weight": 1.0}]}