{"nodes": [{"id": "hex_node", "label": "hex.node.js", "file_type": "code", "source_file": "apps\\frontend\\node_modules\\@exodus\\bytes\\hex.node.js", "source_location": "L1"}, {"id": "hex_node_tohex", "label": "toHex()", "file_type": "code", "source_file": "apps\\frontend\\node_modules\\@exodus\\bytes\\hex.node.js", "source_location": "L9"}], "edges": [{"source": "hex_node", "target": "utils_js", "relation": "imports_from", "confidence": "EXTRACTED", "source_file": "apps\\frontend\\node_modules\\@exodus\\bytes\\hex.node.js", "source_location": "L1", "weight": 1.0}, {"source": "hex_node", "target": "hex_js", "relation": "imports_from", "confidence": "EXTRACTED", "source_file": "apps\\frontend\\node_modules\\@exodus\\bytes\\hex.node.js", "source_location": "L2", "weight": 1.0}, {"source": "hex_node", "target": "hex_node_tohex", "relation": "contains", "confidence": "EXTRACTED", "source_file": "apps\\frontend\\node_modules\\@exodus\\bytes\\hex.node.js", "source_location": "L9", "weight": 1.0}]}