{"nodes": [{"id": "noniterablespread", "label": "nonIterableSpread.js", "file_type": "code", "source_file": "apps\\frontend\\node_modules\\@babel\\runtime\\helpers\\nonIterableSpread.js", "source_location": "L1"}, {"id": "noniterablespread_noniterablespread", "label": "_nonIterableSpread()", "file_type": "code", "source_file": "apps\\frontend\\node_modules\\@babel\\runtime\\helpers\\nonIterableSpread.js", "source_location": "L1"}], "edges": [{"source": "noniterablespread", "target": "noniterablespread_noniterablespread", "relation": "contains", "confidence": "EXTRACTED", "source_file": "apps\\frontend\\node_modules\\@babel\\runtime\\helpers\\nonIterableSpread.js", "source_location": "L1", "weight": 1.0}]}