{"nodes": [{"id": "fontvariant", "label": "fontVariant.js", "file_type": "code", "source_file": "apps\\frontend\\node_modules\\cssstyle\\lib\\properties\\fontVariant.js", "source_location": "L1"}, {"id": "fontvariant_set", "label": "set()", "file_type": "code", "source_file": "apps\\frontend\\node_modules\\cssstyle\\lib\\properties\\fontVariant.js", "source_location": "L41"}, {"id": "fontvariant_get", "label": "get()", "file_type": "code", "source_file": "apps\\frontend\\node_modules\\cssstyle\\lib\\properties\\fontVariant.js", "source_location": "L59"}], "edges": [{"source": "fontvariant", "target": "fontvariant_set", "relation": "contains", "confidence": "EXTRACTED", "source_file": "apps\\frontend\\node_modules\\cssstyle\\lib\\properties\\fontVariant.js", "source_location": "L41", "weight": 1.0}, {"source": "fontvariant", "target": "fontvariant_get", "relation": "contains", "confidence": "EXTRACTED", "source_file": "apps\\frontend\\node_modules\\cssstyle\\lib\\properties\\fontVariant.js", "source_location": "L59", "weight": 1.0}, {"source": "fontvariant_set", "target": "fontvariant_get", "relation": "calls", "confidence": "INFERRED", "source_file": "apps\\frontend\\node_modules\\cssstyle\\lib\\properties\\fontVariant.js", "source_location": "L52", "weight": 0.8}]}