{"nodes": [{"id": "unary", "label": "unary.js", "file_type": "code", "source_file": "apps\\electron\\node_modules\\lodash\\unary.js", "source_location": "L1"}, {"id": "unary_unary", "label": "unary()", "file_type": "code", "source_file": "apps\\electron\\node_modules\\lodash\\unary.js", "source_location": "L18"}], "edges": [{"source": "unary", "target": "unary_unary", "relation": "contains", "confidence": "EXTRACTED", "source_file": "apps\\electron\\node_modules\\lodash\\unary.js", "source_location": "L18", "weight": 1.0}]}