{"nodes": [{"id": "lrucache", "label": "lruCache.js", "file_type": "code", "source_file": "apps\\frontend\\node_modules\\playwright-core\\lib\\utils\\isomorphic\\lruCache.js", "source_location": "L1"}, {"id": "lrucache_lrucache", "label": "LRUCache", "file_type": "code", "source_file": "apps\\frontend\\node_modules\\playwright-core\\lib\\utils\\isomorphic\\lruCache.js", "source_location": "L24"}, {"id": "lrucache_lrucache_constructor", "label": ".constructor()", "file_type": "code", "source_file": "apps\\frontend\\node_modules\\playwright-core\\lib\\utils\\isomorphic\\lruCache.js", "source_location": "L25"}, {"id": "lrucache_lrucache_getorcompute", "label": ".getOrCompute()", "file_type": "code", "source_file": "apps\\frontend\\node_modules\\playwright-core\\lib\\utils\\isomorphic\\lruCache.js", "source_location": "L30"}], "edges": [{"source": "lrucache", "target": "lrucache_lrucache", "relation": "contains", "confidence": "EXTRACTED", "source_file": "apps\\frontend\\node_modules\\playwright-core\\lib\\utils\\isomorphic\\lruCache.js", "source_location": "L24", "weight": 1.0}, {"source": "lrucache_lrucache", "target": "lrucache_lrucache_constructor", "relation": "method", "confidence": "EXTRACTED", "source_file": "apps\\frontend\\node_modules\\playwright-core\\lib\\utils\\isomorphic\\lruCache.js", "source_location": "L25", "weight": 1.0}, {"source": "lrucache_lrucache", "target": "lrucache_lrucache_getorcompute", "relation": "method", "confidence": "EXTRACTED", "source_file": "apps\\frontend\\node_modules\\playwright-core\\lib\\utils\\isomorphic\\lruCache.js", "source_location": "L30", "weight": 1.0}]}