{"nodes": [{"id": "sortedindexof", "label": "sortedIndexOf.js", "file_type": "code", "source_file": "apps\\electron\\node_modules\\lodash\\sortedIndexOf.js", "source_location": "L1"}, {"id": "sortedindexof_sortedindexof", "label": "sortedIndexOf()", "file_type": "code", "source_file": "apps\\electron\\node_modules\\lodash\\sortedIndexOf.js", "source_location": "L20"}], "edges": [{"source": "sortedindexof", "target": "sortedindexof_sortedindexof", "relation": "contains", "confidence": "EXTRACTED", "source_file": "apps\\electron\\node_modules\\lodash\\sortedIndexOf.js", "source_location": "L20", "weight": 1.0}]}