{"nodes": [{"id": "client", "label": "client.ts", "file_type": "code", "source_file": "apps\\frontend\\src\\lib\\api\\client.ts", "source_location": "L1"}, {"id": "client_apicontracterror", "label": "ApiContractError", "file_type": "code", "source_file": "apps\\frontend\\src\\lib\\api\\client.ts", "source_location": "L182"}, {"id": "client_apicontracterror_constructor", "label": ".constructor()", "file_type": "code", "source_file": "apps\\frontend\\src\\lib\\api\\client.ts", "source_location": "L183"}, {"id": "client_apiresponseerror", "label": "ApiResponseError", "file_type": "code", "source_file": "apps\\frontend\\src\\lib\\api\\client.ts", "source_location": "L193"}, {"id": "client_apiresponseerror_constructor", "label": ".constructor()", "file_type": "code", "source_file": "apps\\frontend\\src\\lib\\api\\client.ts", "source_location": "L194"}, {"id": "client_assertrecord", "label": "assertRecord()", "file_type": "code", "source_file": "apps\\frontend\\src\\lib\\api\\client.ts", "source_location": "L206"}, {"id": "client_expectstring", "label": "expectString()", "file_type": "code", "source_file": "apps\\frontend\\src\\lib\\api\\client.ts", "source_location": "L212"}, {"id": "client_expectnullablestring", "label": "expectNullableString()", "file_type": "code", "source_file": "apps\\frontend\\src\\lib\\api\\client.ts", "source_location": "L219"}, {"id": "client_expectboolean", "label": "expectBoolean()", "file_type": "code", "source_file": "apps\\frontend\\src\\lib\\api\\client.ts", "source_location": "L226"}, {"id": "client_expectnumber", "label": "expectNumber()", "file_type": "code", "source_file": "apps\\frontend\\src\\lib\\api\\client.ts", "source_location": "L233"}, {"id": "client_expectjsonobject", "label": "expectJsonObject()", "file_type": "code", "source_file": "apps\\frontend\\src\\lib\\api\\client.ts", "source_location": "L240"}, {"id": "client_expectarray", "label": "expectArray()", "file_type": "code", "source_file": "apps\\frontend\\src\\lib\\api\\client.ts", "source_location": "L245"}, {"id": "client_expectobjectnumbers", "label": "expectObjectNumbers()", "file_type": "code", "source_file": "apps\\frontend\\src\\lib\\api\\client.ts", "source_location": "L253"}, {"id": "client_parseworkspacecontext", "label": "parseWorkspaceContext()", "file_type": "code", "source_file": "apps\\frontend\\src\\lib\\api\\client.ts", "source_location": "L263"}, {"id": "client_parsecommandcentersignal", "label": "parseCommandCenterSignal()", "file_type": "code", "source_file": "apps\\frontend\\src\\lib\\api\\client.ts", "source_location": "L273"}, {"id": "client_parsenextaction", "label": "parseNextAction()", "file_type": "code", "source_file": "apps\\frontend\\src\\lib\\api\\client.ts", "source_location": "L283"}, {"id": "client_parsecommandcenterroute", "label": "parseCommandCenterRoute()", "file_type": "code", "source_file": "apps\\frontend\\src\\lib\\api\\client.ts", "source_location": "L293"}, {"id": "client_parsecommandcenterauditentry", "label": "parseCommandCenterAuditEntry()", "file_type": "code", "source_file": "apps\\frontend\\src\\lib\\api\\client.ts", "source_location": "L304"}, {"id": "client_parseworkspaceobjectsummary", "label": "parseWorkspaceObjectSummary()", "file_type": "code", "source_file": "apps\\frontend\\src\\lib\\api\\client.ts", "source_location": "L319"}, {"id": "client_parseskillworkshopskill", "label": "parseSkillWorkshopSkill()", "file_type": "code", "source_file": "apps\\frontend\\src\\lib\\api\\client.ts", "source_location": "L330"}, {"id": "client_parseskillworkshopversion", "label": "parseSkillWorkshopVersion()", "file_type": "code", "source_file": "apps\\frontend\\src\\lib\\api\\client.ts", "source_location": "L347"}, {"id": "client_parseskillworkshopcomparison", "label": "parseSkillWorkshopComparison()", "file_type": "code", "source_file": "apps\\frontend\\src\\lib\\api\\client.ts", "source_location": "L361"}, {"id": "client_parsestartupsnapshot", "label": "parseStartupSnapshot()", "file_type": "code", "source_file": "apps\\frontend\\src\\lib\\api\\client.ts", "source_location": "L374"}, {"id": "client_parsecommandcentersnapshot", "label": "parseCommandCenterSnapshot()", "file_type": "code", "source_file": "apps\\frontend\\src\\lib\\api\\client.ts", "source_location": "L382"}, {"id": "client_parsepipelineworkbenchsnapshot", "label": "parsePipelineWorkbenchSnapshot()", "file_type": "code", "source_file": "apps\\frontend\\src\\lib\\api\\client.ts", "source_location": "L402"}, {"id": "client_parseskillworkshopsnapshot", "label": "parseSkillWorkshopSnapshot()", "file_type": "code", "source_file": "apps\\frontend\\src\\lib\\api\\client.ts", "source_location": "L414"}, {"id": "client_parsepublishsnapshot", "label": "parsePublishSnapshot()", "file_type": "code", "source_file": "apps\\frontend\\src\\lib\\api\\client.ts", "source_location": "L426"}, {"id": "client_parseprovidersettingssnapshot", "label": "parseProviderSettingsSnapshot()", "file_type": "code", "source_file": "apps\\frontend\\src\\lib\\api\\client.ts", "source_location": "L436"}, {"id": "client_parseapierror", "label": "parseApiError()", "file_type": "code", "source_file": "apps\\frontend\\src\\lib\\api\\client.ts", "source_location": "L444"}, {"id": "client_buildurl", "label": "buildUrl()", "file_type": "code", "source_file": "apps\\frontend\\src\\lib\\api\\client.ts", "source_location": "L457"}, {"id": "client_parseenvelope", "label": "parseEnvelope()", "file_type": "code", "source_file": "apps\\frontend\\src\\lib\\api\\client.ts", "source_location": "L470"}, {"id": "client_request", "label": "request()", "file_type": "code", "source_file": "apps\\frontend\\src\\lib\\api\\client.ts", "source_location": "L512"}, {"id": "client_mutate", "label": "mutate()", "file_type": "code", "source_file": "apps\\frontend\\src\\lib\\api\\client.ts", "source_location": "L529"}], "edges": [{"source": "client", "target": "client_apicontracterror", "relation": "contains", "confidence": "EXTRACTED", "source_file": "apps\\frontend\\src\\lib\\api\\client.ts", "source_location": "L182", "weight": 1.0}, {"source": "client_apicontracterror", "target": "client_apicontracterror_constructor", "relation": "method", "confidence": "EXTRACTED", "source_file": "apps\\frontend\\src\\lib\\api\\client.ts", "source_location": "L183", "weight": 1.0}, {"source": "client", "target": "client_apiresponseerror", "relation": "contains", "confidence": "EXTRACTED", "source_file": "apps\\frontend\\src\\lib\\api\\client.ts", "source_location": "L193", "weight": 1.0}, {"source": "client_apiresponseerror", "target": "client_apiresponseerror_constructor", "relation": "method", "confidence": "EXTRACTED", "source_file": "apps\\frontend\\src\\lib\\api\\client.ts", "source_location": "L194", "weight": 1.0}, {"source": "client", "target": "client_assertrecord", "relation": "contains", "confidence": "EXTRACTED", "source_file": "apps\\frontend\\src\\lib\\api\\client.ts", "source_location": "L206", "weight": 1.0}, {"source": "client", "target": "client_expectstring", "relation": "contains", "confidence": "EXTRACTED", "source_file": "apps\\frontend\\src\\lib\\api\\client.ts", "source_location": "L212", "weight": 1.0}, {"source": "client", "target": "client_expectnullablestring", "relation": "contains", "confidence": "EXTRACTED", "source_file": "apps\\frontend\\src\\lib\\api\\client.ts", "source_location": "L219", "weight": 1.0}, {"source": "client", "target": "client_expectboolean", "relation": "contains", "confidence": "EXTRACTED", "source_file": "apps\\frontend\\src\\lib\\api\\client.ts", "source_location": "L226", "weight": 1.0}, {"source": "client", "target": "client_expectnumber", "relation": "contains", "confidence": "EXTRACTED", "source_file": "apps\\frontend\\src\\lib\\api\\client.ts", "source_location": "L233", "weight": 1.0}, {"source": "client", "target": "client_expectjsonobject", "relation": "contains", "confidence": "EXTRACTED", "source_file": "apps\\frontend\\src\\lib\\api\\client.ts", "source_location": "L240", "weight": 1.0}, {"source": "client", "target": "client_expectarray", "relation": "contains", "confidence": "EXTRACTED", "source_file": "apps\\frontend\\src\\lib\\api\\client.ts", "source_location": "L245", "weight": 1.0}, {"source": "client", "target": "client_expectobjectnumbers", "relation": "contains", "confidence": "EXTRACTED", "source_file": "apps\\frontend\\src\\lib\\api\\client.ts", "source_location": "L253", "weight": 1.0}, {"source": "client", "target": "client_parseworkspacecontext", "relation": "contains", "confidence": "EXTRACTED", "source_file": "apps\\frontend\\src\\lib\\api\\client.ts", "source_location": "L263", "weight": 1.0}, {"source": "client", "target": "client_parsecommandcentersignal", "relation": "contains", "confidence": "EXTRACTED", "source_file": "apps\\frontend\\src\\lib\\api\\client.ts", "source_location": "L273", "weight": 1.0}, {"source": "client", "target": "client_parsenextaction", "relation": "contains", "confidence": "EXTRACTED", "source_file": "apps\\frontend\\src\\lib\\api\\client.ts", "source_location": "L283", "weight": 1.0}, {"source": "client", "target": "client_parsecommandcenterroute", "relation": "contains", "confidence": "EXTRACTED", "source_file": "apps\\frontend\\src\\lib\\api\\client.ts", "source_location": "L293", "weight": 1.0}, {"source": "client", "target": "client_parsecommandcenterauditentry", "relation": "contains", "confidence": "EXTRACTED", "source_file": "apps\\frontend\\src\\lib\\api\\client.ts", "source_location": "L304", "weight": 1.0}, {"source": "client", "target": "client_parseworkspaceobjectsummary", "relation": "contains", "confidence": "EXTRACTED", "source_file": "apps\\frontend\\src\\lib\\api\\client.ts", "source_location": "L319", "weight": 1.0}, {"source": "client", "target": "client_parseskillworkshopskill", "relation": "contains", "confidence": "EXTRACTED", "source_file": "apps\\frontend\\src\\lib\\api\\client.ts", "source_location": "L330", "weight": 1.0}, {"source": "client", "target": "client_parseskillworkshopversion", "relation": "contains", "confidence": "EXTRACTED", "source_file": "apps\\frontend\\src\\lib\\api\\client.ts", "source_location": "L347", "weight": 1.0}, {"source": "client", "target": "client_parseskillworkshopcomparison", "relation": "contains", "confidence": "EXTRACTED", "source_file": "apps\\frontend\\src\\lib\\api\\client.ts", "source_location": "L361", "weight": 1.0}, {"source": "client", "target": "client_parsestartupsnapshot", "relation": "contains", "confidence": "EXTRACTED", "source_file": "apps\\frontend\\src\\lib\\api\\client.ts", "source_location": "L374", "weight": 1.0}, {"source": "client", "target": "client_parsecommandcentersnapshot", "relation": "contains", "confidence": "EXTRACTED", "source_file": "apps\\frontend\\src\\lib\\api\\client.ts", "source_location": "L382", "weight": 1.0}, {"source": "client", "target": "client_parsepipelineworkbenchsnapshot", "relation": "contains", "confidence": "EXTRACTED", "source_file": "apps\\frontend\\src\\lib\\api\\client.ts", "source_location": "L402", "weight": 1.0}, {"source": "client", "target": "client_parseskillworkshopsnapshot", "relation": "contains", "confidence": "EXTRACTED", "source_file": "apps\\frontend\\src\\lib\\api\\client.ts", "source_location": "L414", "weight": 1.0}, {"source": "client", "target": "client_parsepublishsnapshot", "relation": "contains", "confidence": "EXTRACTED", "source_file": "apps\\frontend\\src\\lib\\api\\client.ts", "source_location": "L426", "weight": 1.0}, {"source": "client", "target": "client_parseprovidersettingssnapshot", "relation": "contains", "confidence": "EXTRACTED", "source_file": "apps\\frontend\\src\\lib\\api\\client.ts", "source_location": "L436", "weight": 1.0}, {"source": "client", "target": "client_parseapierror", "relation": "contains", "confidence": "EXTRACTED", "source_file": "apps\\frontend\\src\\lib\\api\\client.ts", "source_location": "L444", "weight": 1.0}, {"source": "client", "target": "client_buildurl", "relation": "contains", "confidence": "EXTRACTED", "source_file": "apps\\frontend\\src\\lib\\api\\client.ts", "source_location": "L457", "weight": 1.0}, {"source": "client", "target": "client_parseenvelope", "relation": "contains", "confidence": "EXTRACTED", "source_file": "apps\\frontend\\src\\lib\\api\\client.ts", "source_location": "L470", "weight": 1.0}, {"source": "client", "target": "client_request", "relation": "contains", "confidence": "EXTRACTED", "source_file": "apps\\frontend\\src\\lib\\api\\client.ts", "source_location": "L512", "weight": 1.0}, {"source": "client", "target": "client_mutate", "relation": "contains", "confidence": "EXTRACTED", "source_file": "apps\\frontend\\src\\lib\\api\\client.ts", "source_location": "L529", "weight": 1.0}, {"source": "client", "target": "electron_client", "relation": "imports_from", "confidence": "EXTRACTED", "source_file": "apps\\frontend\\src\\lib\\api\\client.ts", "source_location": "L557", "weight": 1.0}, {"source": "client_expectnullablestring", "target": "client_expectstring", "relation": "calls", "confidence": "INFERRED", "source_file": "apps\\frontend\\src\\lib\\api\\client.ts", "source_location": "L223", "weight": 0.8}, {"source": "client_expectjsonobject", "target": "client_assertrecord", "relation": "calls", "confidence": "INFERRED", "source_file": "apps\\frontend\\src\\lib\\api\\client.ts", "source_location": "L241", "weight": 0.8}, {"source": "client_expectobjectnumbers", "target": "client_assertrecord", "relation": "calls", "confidence": "INFERRED", "source_file": "apps\\frontend\\src\\lib\\api\\client.ts", "source_location": "L254", "weight": 0.8}, {"source": "client_expectobjectnumbers", "target": "client_expectnumber", "relation": "calls", "confidence": "INFERRED", "source_file": "apps\\frontend\\src\\lib\\api\\client.ts", "source_location": "L258", "weight": 0.8}, {"source": "client_parseworkspacecontext", "target": "client_assertrecord", "relation": "calls", "confidence": "INFERRED", "source_file": "apps\\frontend\\src\\lib\\api\\client.ts", "source_location": "L264", "weight": 0.8}, {"source": "client_parseworkspacecontext", "target": "client_expectstring", "relation": "calls", "confidence": "INFERRED", "source_file": "apps\\frontend\\src\\lib\\api\\client.ts", "source_location": "L266", "weight": 0.8}, {"source": "client_parseworkspacecontext", "target": "client_expectnullablestring", "relation": "calls", "confidence": "INFERRED", "source_file": "apps\\frontend\\src\\lib\\api\\client.ts", "source_location": "L268", "weight": 0.8}, {"source": "client_parsecommandcentersignal", "target": "client_assertrecord", "relation": "calls", "confidence": "INFERRED", "source_file": "apps\\frontend\\src\\lib\\api\\client.ts", "source_location": "L274", "weight": 0.8}, {"source": "client_parsecommandcentersignal", "target": "client_expectstring", "relation": "calls", "confidence": "INFERRED", "source_file": "apps\\frontend\\src\\lib\\api\\client.ts", "source_location": "L276", "weight": 0.8}, {"source": "client_parsenextaction", "target": "client_assertrecord", "relation": "calls", "confidence": "INFERRED", "source_file": "apps\\frontend\\src\\lib\\api\\client.ts", "source_location": "L284", "weight": 0.8}, {"source": "client_parsenextaction", "target": "client_expectstring", "relation": "calls", "confidence": "INFERRED", "source_file": "apps\\frontend\\src\\lib\\api\\client.ts", "source_location": "L286", "weight": 0.8}, {"source": "client_parsecommandcenterroute", "target": "client_assertrecord", "relation": "calls", "confidence": "INFERRED", "source_file": "apps\\frontend\\src\\lib\\api\\client.ts", "source_location": "L294", "weight": 0.8}, {"source": "client_parsecommandcenterroute", "target": "client_expectstring", "relation": "calls", "confidence": "INFERRED", "source_file": "apps\\frontend\\src\\lib\\api\\client.ts", "source_location": "L296", "weight": 0.8}, {"source": "client_parsecommandcenterauditentry", "target": "client_assertrecord", "relation": "calls", "confidence": "INFERRED", "source_file": "apps\\frontend\\src\\lib\\api\\client.ts", "source_location": "L305", "weight": 0.8}, {"source": "client_parsecommandcenterauditentry", "target": "client_expectstring", "relation": "calls", "confidence": "INFERRED", "source_file": "apps\\frontend\\src\\lib\\api\\client.ts", "source_location": "L307", "weight": 0.8}, {"source": "client_parsecommandcenterauditentry", "target": "client_expectnumber", "relation": "calls", "confidence": "INFERRED", "source_file": "apps\\frontend\\src\\lib\\api\\client.ts", "source_location": "L310", "weight": 0.8}, {"source": "client_parsecommandcenterauditentry", "target": "client_expectnullablestring", "relation": "calls", "confidence": "INFERRED", "source_file": "apps\\frontend\\src\\lib\\api\\client.ts", "source_location": "L314", "weight": 0.8}, {"source": "client_parseworkspaceobjectsummary", "target": "client_assertrecord", "relation": "calls", "confidence": "INFERRED", "source_file": "apps\\frontend\\src\\lib\\api\\client.ts", "source_location": "L320", "weight": 0.8}, {"source": "client_parseworkspaceobjectsummary", "target": "client_expectstring", "relation": "calls", "confidence": "INFERRED", "source_file": "apps\\frontend\\src\\lib\\api\\client.ts", "source_location": "L322", "weight": 0.8}, {"source": "client_parseworkspaceobjectsummary", "target": "client_expectnumber", "relation": "calls", "confidence": "INFERRED", "source_file": "apps\\frontend\\src\\lib\\api\\client.ts", "source_location": "L325", "weight": 0.8}, {"source": "client_parseworkspaceobjectsummary", "target": "client_expectjsonobject", "relation": "calls", "confidence": "INFERRED", "source_file": "apps\\frontend\\src\\lib\\api\\client.ts", "source_location": "L326", "weight": 0.8}, {"source": "client_parseskillworkshopskill", "target": "client_assertrecord", "relation": "calls", "confidence": "INFERRED", "source_file": "apps\\frontend\\src\\lib\\api\\client.ts", "source_location": "L331", "weight": 0.8}, {"source": "client_parseskillworkshopskill", "target": "client_expectstring", "relation": "calls", "confidence": "INFERRED", "source_file": "apps\\frontend\\src\\lib\\api\\client.ts", "source_location": "L333", "weight": 0.8}, {"source": "client_parseskillworkshopskill", "target": "client_expectnumber", "relation": "calls", "confidence": "INFERRED", "source_file": "apps\\frontend\\src\\lib\\api\\client.ts", "source_location": "L335", "weight": 0.8}, {"source": "client_parseskillworkshopskill", "target": "client_expectboolean", "relation": "calls", "confidence": "INFERRED", "source_file": "apps\\frontend\\src\\lib\\api\\client.ts", "source_location": "L340", "weight": 0.8}, {"source": "client_parseskillworkshopskill", "target": "client_expectnullablestring", "relation": "calls", "confidence": "INFERRED", "source_file": "apps\\frontend\\src\\lib\\api\\client.ts", "source_location": "L342", "weight": 0.8}, {"source": "client_parseskillworkshopskill", "target": "client_expectjsonobject", "relation": "calls", "confidence": "INFERRED", "source_file": "apps\\frontend\\src\\lib\\api\\client.ts", "source_location": "L343", "weight": 0.8}, {"source": "client_parseskillworkshopversion", "target": "client_assertrecord", "relation": "calls", "confidence": "INFERRED", "source_file": "apps\\frontend\\src\\lib\\api\\client.ts", "source_location": "L348", "weight": 0.8}, {"source": "client_parseskillworkshopversion", "target": "client_expectstring", "relation": "calls", "confidence": "INFERRED", "source_file": "apps\\frontend\\src\\lib\\api\\client.ts", "source_location": "L350", "weight": 0.8}, {"source": "client_parseskillworkshopversion", "target": "client_expectnumber", "relation": "calls", "confidence": "INFERRED", "source_file": "apps\\frontend\\src\\lib\\api\\client.ts", "source_location": "L351", "weight": 0.8}, {"source": "client_parseskillworkshopversion", "target": "client_expectnullablestring", "relation": "calls", "confidence": "INFERRED", "source_file": "apps\\frontend\\src\\lib\\api\\client.ts", "source_location": "L352", "weight": 0.8}, {"source": "client_parseskillworkshopversion", "target": "client_expectboolean", "relation": "calls", "confidence": "INFERRED", "source_file": "apps\\frontend\\src\\lib\\api\\client.ts", "source_location": "L356", "weight": 0.8}, {"source": "client_parseskillworkshopversion", "target": "client_expectjsonobject", "relation": "calls", "confidence": "INFERRED", "source_file": "apps\\frontend\\src\\lib\\api\\client.ts", "source_location": "L357", "weight": 0.8}, {"source": "client_parseskillworkshopcomparison", "target": "client_assertrecord", "relation": "calls", "confidence": "INFERRED", "source_file": "apps\\frontend\\src\\lib\\api\\client.ts", "source_location": "L362", "weight": 0.8}, {"source": "client_parseskillworkshopcomparison", "target": "client_expectstring", "relation": "calls", "confidence": "INFERRED", "source_file": "apps\\frontend\\src\\lib\\api\\client.ts", "source_location": "L364", "weight": 0.8}, {"source": "client_parseskillworkshopcomparison", "target": "client_expectnumber", "relation": "calls", "confidence": "INFERRED", "source_file": "apps\\frontend\\src\\lib\\api\\client.ts", "source_location": "L366", "weight": 0.8}, {"source": "client_parseskillworkshopcomparison", "target": "client_expectjsonobject", "relation": "calls", "confidence": "INFERRED", "source_file": "apps\\frontend\\src\\lib\\api\\client.ts", "source_location": "L369", "weight": 0.8}, {"source": "client_parsestartupsnapshot", "target": "client_assertrecord", "relation": "calls", "confidence": "INFERRED", "source_file": "apps\\frontend\\src\\lib\\api\\client.ts", "source_location": "L375", "weight": 0.8}, {"source": "client_parsestartupsnapshot", "target": "client_expectarray", "relation": "calls", "confidence": "INFERRED", "source_file": "apps\\frontend\\src\\lib\\api\\client.ts", "source_location": "L377", "weight": 0.8}, {"source": "client_parsestartupsnapshot", "target": "client_expectboolean", "relation": "calls", "confidence": "INFERRED", "source_file": "apps\\frontend\\src\\lib\\api\\client.ts", "source_location": "L378", "weight": 0.8}, {"source": "client_parsecommandcentersnapshot", "target": "client_assertrecord", "relation": "calls", "confidence": "INFERRED", "source_file": "apps\\frontend\\src\\lib\\api\\client.ts", "source_location": "L383", "weight": 0.8}, {"source": "client_parsecommandcentersnapshot", "target": "client_expectstring", "relation": "calls", "confidence": "INFERRED", "source_file": "apps\\frontend\\src\\lib\\api\\client.ts", "source_location": "L385", "weight": 0.8}, {"source": "client_parsecommandcentersnapshot", "target": "client_expectnullablestring", "relation": "calls", "confidence": "INFERRED", "source_file": "apps\\frontend\\src\\lib\\api\\client.ts", "source_location": "L386", "weight": 0.8}, {"source": "client_parsecommandcentersnapshot", "target": "client_expectobjectnumbers", "relation": "calls", "confidence": "INFERRED", "source_file": "apps\\frontend\\src\\lib\\api\\client.ts", "source_location": "L391", "weight": 0.8}, {"source": "client_parsecommandcentersnapshot", "target": "client_expectarray", "relation": "calls", "confidence": "INFERRED", "source_file": "apps\\frontend\\src\\lib\\api\\client.ts", "source_location": "L392", "weight": 0.8}, {"source": "client_parsecommandcentersnapshot", "target": "client_expectnumber", "relation": "calls", "confidence": "INFERRED", "source_file": "apps\\frontend\\src\\lib\\api\\client.ts", "source_location": "L397", "weight": 0.8}, {"source": "client_parsepipelineworkbenchsnapshot", "target": "client_assertrecord", "relation": "calls", "confidence": "INFERRED", "source_file": "apps\\frontend\\src\\lib\\api\\client.ts", "source_location": "L403", "weight": 0.8}, {"source": "client_parsepipelineworkbenchsnapshot", "target": "client_expectstring", "relation": "calls", "confidence": "INFERRED", "source_file": "apps\\frontend\\src\\lib\\api\\client.ts", "source_location": "L405", "weight": 0.8}, {"source": "client_parsepipelineworkbenchsnapshot", "target": "client_expectarray", "relation": "calls", "confidence": "INFERRED", "source_file": "apps\\frontend\\src\\lib\\api\\client.ts", "source_location": "L408", "weight": 0.8}, {"source": "client_parsepipelineworkbenchsnapshot", "target": "client_expectboolean", "relation": "calls", "confidence": "INFERRED", "source_file": "apps\\frontend\\src\\lib\\api\\client.ts", "source_location": "L410", "weight": 0.8}, {"source": "client_parseskillworkshopsnapshot", "target": "client_assertrecord", "relation": "calls", "confidence": "INFERRED", "source_file": "apps\\frontend\\src\\lib\\api\\client.ts", "source_location": "L415", "weight": 0.8}, {"source": "client_parseskillworkshopsnapshot", "target": "client_expectstring", "relation": "calls", "confidence": "INFERRED", "source_file": "apps\\frontend\\src\\lib\\api\\client.ts", "source_location": "L417", "weight": 0.8}, {"source": "client_parseskillworkshopsnapshot", "target": "client_expectarray", "relation": "calls", "confidence": "INFERRED", "source_file": "apps\\frontend\\src\\lib\\api\\client.ts", "source_location": "L419", "weight": 0.8}, {"source": "client_parseskillworkshopsnapshot", "target": "client_parseskillworkshopskill", "relation": "calls", "confidence": "INFERRED", "source_file": "apps\\frontend\\src\\lib\\api\\client.ts", "source_location": "L420", "weight": 0.8}, {"source": "client_parseskillworkshopsnapshot", "target": "client_parseskillworkshopcomparison", "relation": "calls", "confidence": "INFERRED", "source_file": "apps\\frontend\\src\\lib\\api\\client.ts", "source_location": "L422", "weight": 0.8}, {"source": "client_parsepublishsnapshot", "target": "client_assertrecord", "relation": "calls", "confidence": "INFERRED", "source_file": "apps\\frontend\\src\\lib\\api\\client.ts", "source_location": "L427", "weight": 0.8}, {"source": "client_parsepublishsnapshot", "target": "client_expectstring", "relation": "calls", "confidence": "INFERRED", "source_file": "apps\\frontend\\src\\lib\\api\\client.ts", "source_location": "L429", "weight": 0.8}, {"source": "client_parsepublishsnapshot", "target": "client_expectarray", "relation": "calls", "confidence": "INFERRED", "source_file": "apps\\frontend\\src\\lib\\api\\client.ts", "source_location": "L431", "weight": 0.8}, {"source": "client_parseprovidersettingssnapshot", "target": "client_assertrecord", "relation": "calls", "confidence": "INFERRED", "source_file": "apps\\frontend\\src\\lib\\api\\client.ts", "source_location": "L437", "weight": 0.8}, {"source": "client_parseprovidersettingssnapshot", "target": "client_expectarray", "relation": "calls", "confidence": "INFERRED", "source_file": "apps\\frontend\\src\\lib\\api\\client.ts", "source_location": "L439", "weight": 0.8}, {"source": "client_parseprovidersettingssnapshot", "target": "client_expectjsonobject", "relation": "calls", "confidence": "INFERRED", "source_file": "apps\\frontend\\src\\lib\\api\\client.ts", "source_location": "L440", "weight": 0.8}, {"source": "client_parseapierror", "target": "client_assertrecord", "relation": "calls", "confidence": "INFERRED", "source_file": "apps\\frontend\\src\\lib\\api\\client.ts", "source_location": "L445", "weight": 0.8}, {"source": "client_parseapierror", "target": "client_expectstring", "relation": "calls", "confidence": "INFERRED", "source_file": "apps\\frontend\\src\\lib\\api\\client.ts", "source_location": "L451", "weight": 0.8}, {"source": "client_parseapierror", "target": "client_expectjsonobject", "relation": "calls", "confidence": "INFERRED", "source_file": "apps\\frontend\\src\\lib\\api\\client.ts", "source_location": "L453", "weight": 0.8}, {"source": "client_parseenvelope", "target": "client_assertrecord", "relation": "calls", "confidence": "INFERRED", "source_file": "apps\\frontend\\src\\lib\\api\\client.ts", "source_location": "L484", "weight": 0.8}, {"source": "client_parseenvelope", "target": "client_parseapierror", "relation": "calls", "confidence": "INFERRED", "source_file": "apps\\frontend\\src\\lib\\api\\client.ts", "source_location": "L495", "weight": 0.8}, {"source": "client_request", "target": "client_buildurl", "relation": "calls", "confidence": "INFERRED", "source_file": "apps\\frontend\\src\\lib\\api\\client.ts", "source_location": "L517", "weight": 0.8}, {"source": "client_request", "target": "client_parseenvelope", "relation": "calls", "confidence": "INFERRED", "source_file": "apps\\frontend\\src\\lib\\api\\client.ts", "source_location": "L525", "weight": 0.8}, {"source": "client_mutate", "target": "client_buildurl", "relation": "calls", "confidence": "INFERRED", "source_file": "apps\\frontend\\src\\lib\\api\\client.ts", "source_location": "L536", "weight": 0.8}, {"source": "client_mutate", "target": "client_parseenvelope", "relation": "calls", "confidence": "INFERRED", "source_file": "apps\\frontend\\src\\lib\\api\\client.ts", "source_location": "L546", "weight": 0.8}]}