{"nodes": [{"id": "no_floating_promises_d", "label": "no-floating-promises.d.ts", "file_type": "code", "source_file": "apps\\frontend\\node_modules\\@typescript-eslint\\eslint-plugin\\dist\\rules\\no-floating-promises.d.ts", "source_location": "L1"}], "edges": [{"source": "no_floating_promises_d", "target": "utils", "relation": "imports_from", "confidence": "EXTRACTED", "source_file": "apps\\frontend\\node_modules\\@typescript-eslint\\eslint-plugin\\dist\\rules\\no-floating-promises.d.ts", "source_location": "L1", "weight": 1.0}, {"source": "no_floating_promises_d", "target": "util", "relation": "imports_from", "confidence": "EXTRACTED", "source_file": "apps\\frontend\\node_modules\\@typescript-eslint\\eslint-plugin\\dist\\rules\\no-floating-promises.d.ts", "source_location": "L2", "weight": 1.0}]}